[{"categoria_superior":"0","codigo":"0.01","codigo_dre":"","conta_despesa":"N","conta_inativa":"N","conta_receita":"N","dadosDRE":{},"definida_pelo_usuario":"N","descricao":"Transferência","descricao_padrao":"Transferência","id_conta_contabil":"","nao_exibir":"S","natureza":"","tag_conta_contabil":"","tipo_categoria":"","totalizadora":"S","transferencia":"S"},{"categoria_superior":"0.01","codigo":"0.01.01","codigo_dre":"","conta_despesa":"N","conta_inativa":"N","conta_receita":"S","dadosDRE":{},"definida_pelo_usuario":"N","descricao":"Entrada de Transferência","descricao_padrao":"Entrada de Transferência","id_conta_contabil":"","nao_exibir":"S","natureza":"","tag_conta_contabil":"","tipo_categoria":"","totalizadora":"N","transferencia":"S"},{"categoria_superior":"0.01","codigo":"0.01.02","codigo_dre":"","conta_despesa":"S","conta_inativa":"N","conta_receita":"N","dadosDRE":{},"definida_pelo_usuario":"N","descricao":"Saída de Transferência","descricao_padrao":"Saída de Transferência","id_conta_contabil":"","nao_exibir":"S","natureza":"","tag_conta_contabil":"","tipo_categoria":"","totalizadora":"N","transferencia":"S"},{"categoria_superior":"1","codigo":"1.01","codigo_dre":"","conta_despesa":"N","conta_inativa":"N","conta_receita":"S","dadosDRE":{},"definida_pelo_usuario":"N","descricao":"Receitas Diretas","descricao_padrao":"Receitas Diretas","id_conta_contabil":"","nao_exibir":"N","natureza":"","tag_conta_contabil":"","tipo_categoria":"","totalizadora":"S","transferencia":"N"},{"categoria_superior":"1.01","codigo":"1.01.01","codigo_dre":"1.01.01","conta_despesa":"N","conta_inativa":"N","conta_receita":"S","dadosDRE":{"codigoDRE":"1.01.01","descricaoDRE":"Receita Bruta de Vendas","naoExibirDRE":"N","nivelDRE":3,"sinalDRE":"+","totalizaDRE":"N"},"definida_pelo_usuario":"N","descricao":"Portaria/Limpeza","descricao_padrao":"Portaria/Limpeza","id_conta_contabil":"","nao_exibir":"N","natureza":"Esta categoria deve ser utilizada para receitas provenientes de vendas de produtos fabricados.","tag_conta_contabil":"","tipo_categoria":"","totalizadora":"N","transferencia":"N"},{"categoria_superior":"1.01","codigo":"1.01.02","codigo_dre":"1.01.01","conta_despesa":"N","conta_inativa":"N","conta_receita":"S","dadosDRE":{"codigoDRE":"1.01.01","descricaoDRE":"Receita Bruta de Vendas","naoExibirDRE":"N","nivelDRE":3,"sinalDRE":"+","totalizaDRE":"N"},"definida_pelo_usuario":"N","descricao":"Monitoramento Remoto","descricao_padrao":"Monitoramento Remoto","id_conta_contabil":"","nao_exibir":"N","natureza":"Esta categoria deve ser utilizada para receitas provenientes de serviços prestados a clientes. Não utilizar caso existam produtos envolvidos na prestação de serviços.","tag_conta_contabil":"","tipo_categoria":"","totalizadora":"N","transferencia":"N"},{"categoria_superior":"1.01","codigo":"1.01.03","codigo_dre":"1.01.01","conta_despesa":"N","conta_inativa":"N","conta_receita":"S","dadosDRE":{"codigoDRE":"1.01.01","descricaoDRE":"Receita Bruta de Vendas","naoExibirDRE":"N","nivelDRE":3,"sinalDRE":"+","totalizaDRE":"N"},"definida_pelo_usuario":"N","descricao":"Portaria","descricao_padrao":"Portaria","id_conta_contabil":"","nao_exibir":"N","natureza":"Esta categoria deve ser utilizada para receitas provenientes de revendas de produtos.","tag_conta_contabil":"","tipo_categoria":"","totalizadora":"N","transferencia":"N"},{"categoria_superior":"1.01","codigo":"1.01.34","codigo_dre":"1.01.01","conta_despesa":"N","conta_inativa":"N","conta_receita":"S","dadosDRE":{"codigoDRE":"1.01.01","descricaoDRE":"Receita Bruta de Vendas","naoExibirDRE":"N","nivelDRE":3,"sinalDRE":"+","totalizaDRE":"N"},"definida_pelo_usuario":"S","descricao":"MOV TIT COB DISP 13/10S","descricao_padrao":"MOV TIT COB DISP 13/10S","id_conta_contabil":"","nao_exibir":"N","natureza":"","tag_conta_contabil":"","tipo_categoria":"","totalizadora":"N","transferencia":"N"},{"categoria_superior":"1.01","codigo":"1.01.35","codigo_dre":"","conta_despesa":"N","conta_inativa":"N","conta_receita":"S","dadosDRE":{},"definida_pelo_usuario":"S","descricao":"Portaria Ronda","descricao_padrao":"Portaria Ronda","id_conta_contabil":"1.1.2.01.000001","nao_exibir":"N","natureza":"","tag_conta_contabil":"CLIENTES","tipo_categoria":"","totalizadora":"N","transferencia":"N"},{"categoria_superior":"1.01","codigo":"1.01.36","codigo_dre":"","conta_despesa":"N","conta_inativa":"N","conta_receita":"S","dadosDRE":{},"definida_pelo_usuario":"S","descricao":"NOTA CREDITO BENEFICIOS","descricao_padrao":"NOTA CREDITO BENEFICIOS","id_conta_contabil":"1.1.2.01.000001","nao_exibir":"N","natureza":"","tag_conta_contabil":"CLIENTES","tipo_categoria":"","totalizadora":"N","transferencia":"N"},{"categoria_superior":"1.01","codigo":"1.01.37","codigo_dre":"","conta_despesa":"N","conta_inativa":"N","conta_receita":"S","dadosDRE":{},"definida_pelo_usuario":"S","descricao":"Manutenção CFTV","descricao_padrao":"Manutenção CFTV","id_conta_contabil":"4.2.1.06.000002","nao_exibir":"N","natureza":"","tag_conta_contabil":"MANUTENÇÃO E REPARO","tipo_categoria":"","totalizadora":"N","transferencia":"N"},{"categoria_superior":"1.01","codigo":"1.01.38","codigo_dre":"","conta_despesa":"N","conta_inativa":"N","conta_receita":"S","dadosDRE":{},"definida_pelo_usuario":"S","descricao":"Limpeza e Manutenção","descricao_padrao":"Limpeza e Manutenção","id_conta_contabil":"1.1.2.01.000001","nao_exibir":"N","natureza":"","tag_conta_contabil":"CLIENTES","tipo_categoria":"","totalizadora":"N","transferencia":"N"},{"categoria_superior":"1.01","codigo":"1.01.39","codigo_dre":"","conta_despesa":"N","conta_inativa":"N","conta_receita":"S","dadosDRE":{},"definida_pelo_usuario":"S","descricao":"Torre Monitorada","descricao_padrao":"Torre Monitorada","id_conta_contabil":"","nao_exibir":"N","natureza":"","tag_conta_contabil":"","tipo_categoria":"","totalizadora":"N","transferencia":"N"},{"categoria_superior":"1.01","codigo":"1.01.40","codigo_dre":"","conta_despesa":"N","conta_inativa":"N","conta_receita":"S","dadosDRE":{},"definida_pelo_usuario":"S","descricao":"Instalação Reparo Cerca Elétrica","descricao_padrao":"Instalação Reparo Cerca Elétrica","id_conta_contabil":"","nao_exibir":"N","natureza":"","tag_conta_contabil":"","tipo_categoria":"","totalizadora":"N","transferencia":"N"},{"categoria_superior":"1.01","codigo":"1.01.41","codigo_dre":"","conta_despesa":"N","conta_inativa":"N","conta_receita":"S","dadosDRE":{},"definida_pelo_usuario":"S","descricao":"Limpeza de Vidros","descricao_padrao":"Limpeza de Vidros","id_conta_contabil":"","nao_exibir":"N","natureza":"","tag_conta_contabil":"","tipo_categoria":"","totalizadora":"N","transferencia":"N"},{"categoria_superior":"1.01","codigo":"1.01.42","codigo_dre":"","conta_despesa":"N","conta_inativa":"N","conta_receita":"S","dadosDRE":{},"definida_pelo_usuario":"S","descricao":"Apoio Operacional","descricao_padrao":"Apoio Operacional","id_conta_contabil":"","nao_exibir":"N","natureza":"","tag_conta_contabil":"","tipo_categoria":"","totalizadora":"N","transferencia":"N"},{"categoria_superior":"1.01","codigo":"1.01.43","codigo_dre":"","conta_despesa":"N","conta_inativa":"N","conta_receita":"S","dadosDRE":{},"definida_pelo_usuario":"S","descricao":"Empréstimo","descricao_padrao":"Empréstimo","id_conta_contabil":"4.2.2.06.000012","nao_exibir":"N","natureza":"","tag_conta_contabil":"EMPRESTIMO / FINANCIAMENTO","tipo_categoria":"","totalizadora":"N","transferencia":"N"},{"categoria_superior":"1.01","codigo":"1.01.44","codigo_dre":"","conta_despesa":"N","conta_inativa":"N","conta_receita":"S","dadosDRE":{},"definida_pelo_usuario":"S","descricao":"Resgate Invest 13°","descricao_padrao":"Resgate Invest 13°","id_conta_contabil":"1.1.2.01.000033","nao_exibir":"N","natureza":"","tag_conta_contabil":"HBR 51 - INVESTIMENTOS IMOBILIARIOS LTDA.","tipo_categoria":"","totalizadora":"N","transferencia":"N"},{"categoria_superior":"1.01","codigo":"1.01.45","codigo_dre":"","conta_despesa":"N","conta_inativa":"N","conta_receita":"S","dadosDRE":{},"definida_pelo_usuario":"S","descricao":"Prestação de Serviços","descricao_padrao":"Prestação de Serviços","id_conta_contabil":"","nao_exibir":"N","natureza":"","tag_conta_contabil":"","tipo_categoria":"","totalizadora":"N","transferencia":"N"},{"categoria_superior":"1.01","codigo":"1.01.46","codigo_dre":"","conta_despesa":"N","conta_inativa":"N","conta_receita":"S","dadosDRE":{},"definida_pelo_usuario":"S","descricao":"Substituição de Plantas","descricao_padrao":"Substituição de Plantas","id_conta_contabil":"","nao_exibir":"N","natureza":"","tag_conta_contabil":"","tipo_categoria":"","totalizadora":"N","transferencia":"N"},{"categoria_superior":"1.01","codigo":"1.01.47","codigo_dre":"","conta_despesa":"N","conta_inativa":"N","conta_receita":"S","dadosDRE":{},"definida_pelo_usuario":"S","descricao":"Portaria/Limpeza/Zeladoria","descricao_padrao":"Portaria/Limpeza/Zeladoria","id_conta_contabil":"","nao_exibir":"N","natureza":"","tag_conta_contabil":"","tipo_categoria":"","totalizadora":"N","transferencia":"N"},{"categoria_superior":"1.01","codigo":"1.01.48","codigo_dre":"","conta_despesa":"N","conta_inativa":"N","conta_receita":"S","dadosDRE":{},"definida_pelo_usuario":"S","descricao":"Transferência Charles","descricao_padrao":"Transferência Charles","id_conta_contabil":"1.1.3.10.000001","nao_exibir":"N","natureza":"","tag_conta_contabil":"CONTA CORRENTE - SÓCIOS","tipo_categoria":"","totalizadora":"N","transferencia":"N"},{"categoria_superior":"1.01","codigo":"1.01.49","codigo_dre":"","conta_despesa":"N","conta_inativa":"N","conta_receita":"S","dadosDRE":{},"definida_pelo_usuario":"S","descricao":"Transferência Agill Service","descricao_padrao":"Transferência Agill Service","id_conta_contabil":"1.2.2.11.000001","nao_exibir":"N","natureza":"","tag_conta_contabil":"AGILL SERVICE EM LIMPEZA E SERVICOS LTDA","tipo_categoria":"","totalizadora":"N","transferencia":"N"},{"categoria_superior":"1.01","codigo":"1.01.50","codigo_dre":"","conta_despesa":"N","conta_inativa":"N","conta_receita":"S","dadosDRE":{},"definida_pelo_usuario":"S","descricao":"Controlador de Acesso e Limpeza","descricao_padrao":"Controlador de Acesso e Limpeza","id_conta_contabil":"","nao_exibir":"N","natureza":"","tag_conta_contabil":"","tipo_categoria":"","totalizadora":"N","transferencia":"N"},{"categoria_superior":"1.01","codigo":"1.01.51","codigo_dre":"","conta_despesa":"N","conta_inativa":"N","conta_receita":"S","dadosDRE":{},"definida_pelo_usuario":"S","descricao":"Controlador de Acesso Extra","descricao_padrao":"Controlador de Acesso Extra","id_conta_contabil":"","nao_exibir":"N","natureza":"","tag_conta_contabil":"","tipo_categoria":"","totalizadora":"N","transferencia":"N"},{"categoria_superior":"1.01","codigo":"1.01.52","codigo_dre":"","conta_despesa":"N","conta_inativa":"N","conta_receita":"S","dadosDRE":{},"definida_pelo_usuario":"S","descricao":"Controlador de Acesso","descricao_padrao":"Controlador de Acesso","id_conta_contabil":"","nao_exibir":"N","natureza":"","tag_conta_contabil":"","tipo_categoria":"","totalizadora":"N","transferencia":"N"},{"categoria_superior":"1.01","codigo":"1.01.53","codigo_dre":"","conta_despesa":"N","conta_inativa":"N","conta_receita":"S","dadosDRE":{},"definida_pelo_usuario":"S","descricao":"Tar Contrat/Renov Cta Garant","descricao_padrao":"Tar Contrat/Renov Cta Garant","id_conta_contabil":"4.2.2.06.000011","nao_exibir":"N","natureza":"","tag_conta_contabil":"TARIFA BANCÁRIA","tipo_categoria":"","totalizadora":"N","transferencia":"N"},{"categoria_superior":"1.01","codigo":"1.01.54","codigo_dre":"","conta_despesa":"N","conta_inativa":"N","conta_receita":"S","dadosDRE":{},"definida_pelo_usuario":"S","descricao":"Tarifa Pix QRCode","descricao_padrao":"Tarifa Pix QRCode","id_conta_contabil":"4.2.2.06.000011","nao_exibir":"N","natureza":"","tag_conta_contabil":"TARIFA BANCÁRIA","tipo_categoria":"","totalizadora":"N","transferencia":"N"},{"categoria_superior":"1.01","codigo":"1.01.55","codigo_dre":"","conta_despesa":"N","conta_inativa":"N","conta_receita":"S","dadosDRE":{},"definida_pelo_usuario":"S","descricao":"Cobertura LIS","descricao_padrao":"Cobertura LIS","id_conta_contabil":"2.1.1.01.000002","nao_exibir":"N","natureza":"","tag_conta_contabil":"OPERACAO CONTA GARANTIDA","tipo_categoria":"","totalizadora":"N","transferencia":"N"},{"categoria_superior":"1.01","codigo":"1.01.56","codigo_dre":"","conta_despesa":"N","conta_inativa":"N","conta_receita":"S","dadosDRE":{},"definida_pelo_usuario":"S","descricao":"+ Cobertura Conta Garantida","descricao_padrao":"+ Cobertura Conta Garantida","id_conta_contabil":"2.1.1.01.000002","nao_exibir":"N","natureza":"","tag_conta_contabil":"OPERACAO CONTA GARANTIDA","tipo_categoria":"","totalizadora":"N","transferencia":"N"},{"categoria_superior":"1.01","codigo":"1.01.57","codigo_dre":"","conta_despesa":"N","conta_inativa":"N","conta_receita":"S","dadosDRE":{},"definida_pelo_usuario":"S","descricao":"Cartão de Crédito Empresa","descricao_padrao":"Cartão de Crédito Empresa","id_conta_contabil":"4.2.2.04.000008","nao_exibir":"N","natureza":"","tag_conta_contabil":"CARTÃO DE CRÉDITO","tipo_categoria":"","totalizadora":"N","transferencia":"N"},{"categoria_superior":"1.01","codigo":"1.01.58","codigo_dre":"","conta_despesa":"N","conta_inativa":"N","conta_receita":"S","dadosDRE":{},"definida_pelo_usuario":"S","descricao":"Tarifa Pix QRCode Liquida","descricao_padrao":"Tarifa Pix QRCode Liquida","id_conta_contabil":"4.2.2.06.000011","nao_exibir":"N","natureza":"","tag_conta_contabil":"TARIFA BANCÁRIA","tipo_categoria":"","totalizadora":"N","transferencia":"N"},{"categoria_superior":"1.01","codigo":"1.01.59","codigo_dre":"1.01.01","conta_despesa":"N","conta_inativa":"N","conta_receita":"S","dadosDRE":{"codigoDRE":"1.01.01","descricaoDRE":"Receita Bruta de Vendas","naoExibirDRE":"N","nivelDRE":3,"sinalDRE":"+","totalizaDRE":"N"},"definida_pelo_usuario":"S","descricao":"Monitoramento Remota Concessionária","descricao_padrao":"Monitoramento Remota Concessionária","id_conta_contabil":"","nao_exibir":"N","natureza":"","tag_conta_contabil":"","tipo_categoria":"","totalizadora":"N","transferencia":"N"},{"categoria_superior":"1.01","codigo":"1.01.60","codigo_dre":"1.01.01","conta_despesa":"N","conta_inativa":"N","conta_receita":"S","dadosDRE":{"codigoDRE":"1.01.01","descricaoDRE":"Receita Bruta de Vendas","naoExibirDRE":"N","nivelDRE":3,"sinalDRE":"+","totalizaDRE":"N"},"definida_pelo_usuario":"S","descricao":"Monitoramento Remoto Funilaria","descricao_padrao":"Monitoramento Remoto Funilaria","id_conta_contabil":"","nao_exibir":"N","natureza":"","tag_conta_contabil":"","tipo_categoria":"","totalizadora":"N","transferencia":"N"},{"categoria_superior":"1.01","codigo":"1.01.61","codigo_dre":"1.01.01","conta_despesa":"N","conta_inativa":"N","conta_receita":"S","dadosDRE":{"codigoDRE":"1.01.01","descricaoDRE":"Receita Bruta de Vendas","naoExibirDRE":"N","nivelDRE":3,"sinalDRE":"+","totalizaDRE":"N"},"definida_pelo_usuario":"S","descricao":"Portaria Jundiaí 24 Hs.","descricao_padrao":"Portaria Jundiaí 24 Hs.","id_conta_contabil":"","nao_exibir":"N","natureza":"","tag_conta_contabil":"","tipo_categoria":"","totalizadora":"N","transferencia":"N"},{"categoria_superior":"1.01","codigo":"1.01.62","codigo_dre":"1.01.01","conta_despesa":"N","conta_inativa":"N","conta_receita":"S","dadosDRE":{"codigoDRE":"1.01.01","descricaoDRE":"Receita Bruta de Vendas","naoExibirDRE":"N","nivelDRE":3,"sinalDRE":"+","totalizaDRE":"N"},"definida_pelo_usuario":"S","descricao":"Portaria Controle de Acesso","descricao_padrao":"Portaria Controle de Acesso","id_conta_contabil":"","nao_exibir":"N","natureza":"","tag_conta_contabil":"","tipo_categoria":"","totalizadora":"N","transferencia":"N"},{"categoria_superior":"1.01","codigo":"1.01.63","codigo_dre":"1.01.01","conta_despesa":"N","conta_inativa":"N","conta_receita":"S","dadosDRE":{"codigoDRE":"1.01.01","descricaoDRE":"Receita Bruta de Vendas","naoExibirDRE":"N","nivelDRE":3,"sinalDRE":"+","totalizaDRE":"N"},"definida_pelo_usuario":"S","descricao":"Limpeza Extra","descricao_padrao":"Limpeza Extra","id_conta_contabil":"","nao_exibir":"N","natureza":"","tag_conta_contabil":"","tipo_categoria":"","totalizadora":"N","transferencia":"N"},{"categoria_superior":"1.01","codigo":"1.01.64","codigo_dre":"1.01.01","conta_despesa":"N","conta_inativa":"N","conta_receita":"S","dadosDRE":{"codigoDRE":"1.01.01","descricaoDRE":"Receita Bruta de Vendas","naoExibirDRE":"N","nivelDRE":3,"sinalDRE":"+","totalizaDRE":"N"},"definida_pelo_usuario":"S","descricao":"Portaria 12 Hs Diurno","descricao_padrao":"Portaria 12 Hs Diurno","id_conta_contabil":"","nao_exibir":"N","natureza":"","tag_conta_contabil":"","tipo_categoria":"","totalizadora":"N","transferencia":"N"},{"categoria_superior":"1.01","codigo":"1.01.65","codigo_dre":"1.01.01","conta_despesa":"N","conta_inativa":"N","conta_receita":"S","dadosDRE":{"codigoDRE":"1.01.01","descricaoDRE":"Receita Bruta de Vendas","naoExibirDRE":"N","nivelDRE":3,"sinalDRE":"+","totalizaDRE":"N"},"definida_pelo_usuario":"S","descricao":"Limpeza/Copa","descricao_padrao":"Limpeza/Copa","id_conta_contabil":"","nao_exibir":"N","natureza":"","tag_conta_contabil":"","tipo_categoria":"","totalizadora":"N","transferencia":"N"},{"categoria_superior":"1.01","codigo":"1.01.66","codigo_dre":"1.01.01","conta_despesa":"N","conta_inativa":"N","conta_receita":"S","dadosDRE":{"codigoDRE":"1.01.01","descricaoDRE":"Receita Bruta de Vendas","naoExibirDRE":"N","nivelDRE":3,"sinalDRE":"+","totalizaDRE":"N"},"definida_pelo_usuario":"S","descricao":"Limpeza Concessionária","descricao_padrao":"Limpeza Concessionária","id_conta_contabil":"","nao_exibir":"N","natureza":"","tag_conta_contabil":"","tipo_categoria":"","totalizadora":"N","transferencia":"N"},{"categoria_superior":"1.01","codigo":"1.01.67","codigo_dre":"1.01.01","conta_despesa":"N","conta_inativa":"N","conta_receita":"S","dadosDRE":{"codigoDRE":"1.01.01","descricaoDRE":"Receita Bruta de Vendas","naoExibirDRE":"N","nivelDRE":3,"sinalDRE":"+","totalizaDRE":"N"},"definida_pelo_usuario":"S","descricao":"Limpeza Funilaria","descricao_padrao":"Limpeza Funilaria","id_conta_contabil":"","nao_exibir":"N","natureza":"","tag_conta_contabil":"","tipo_categoria":"","totalizadora":"N","transferencia":"N"},{"categoria_superior":"1.01","codigo":"1.01.68","codigo_dre":"1.01.01","conta_despesa":"N","conta_inativa":"N","conta_receita":"S","dadosDRE":{"codigoDRE":"1.01.01","descricaoDRE":"Receita Bruta de Vendas","naoExibirDRE":"N","nivelDRE":3,"sinalDRE":"+","totalizaDRE":"N"},"definida_pelo_usuario":"S","descricao":"Limpeza Volante Comp. Loja/Funilária","descricao_padrao":"Limpeza Volante Comp. Loja/Funilária","id_conta_contabil":"","nao_exibir":"N","natureza":"","tag_conta_contabil":"","tipo_categoria":"","totalizadora":"N","transferencia":"N"},{"categoria_superior":"1.01","codigo":"1.01.69","codigo_dre":"1.01.01","conta_despesa":"N","conta_inativa":"N","conta_receita":"S","dadosDRE":{"codigoDRE":"1.01.01","descricaoDRE":"Receita Bruta de Vendas","naoExibirDRE":"N","nivelDRE":3,"sinalDRE":"+","totalizaDRE":"N"},"definida_pelo_usuario":"S","descricao":"Limpeza Loja e Oficina","descricao_padrao":"Limpeza Loja e Oficina","id_conta_contabil":"","nao_exibir":"N","natureza":"","tag_conta_contabil":"","tipo_categoria":"","totalizadora":"N","transferencia":"N"},{"categoria_superior":"1.01","codigo":"1.01.70","codigo_dre":"1.01.01","conta_despesa":"N","conta_inativa":"N","conta_receita":"S","dadosDRE":{"codigoDRE":"1.01.01","descricaoDRE":"Receita Bruta de Vendas","naoExibirDRE":"N","nivelDRE":3,"sinalDRE":"+","totalizaDRE":"N"},"definida_pelo_usuario":"S","descricao":"Limpeza Volante","descricao_padrao":"Limpeza Volante","id_conta_contabil":"","nao_exibir":"N","natureza":"","tag_conta_contabil":"","tipo_categoria":"","totalizadora":"N","transferencia":"N"},{"categoria_superior":"1.01","codigo":"1.01.71","codigo_dre":"1.01.01","conta_despesa":"N","conta_inativa":"N","conta_receita":"S","dadosDRE":{"codigoDRE":"1.01.01","descricaoDRE":"Receita Bruta de Vendas","naoExibirDRE":"N","nivelDRE":3,"sinalDRE":"+","totalizaDRE":"N"},"definida_pelo_usuario":"S","descricao":"Limpeza","descricao_padrao":"Limpeza","id_conta_contabil":"","nao_exibir":"N","natureza":"","tag_conta_contabil":"","tipo_categoria":"","totalizadora":"N","transferencia":"N"},{"categoria_superior":"1.01","codigo":"1.01.72","codigo_dre":"1.01.01","conta_despesa":"N","conta_inativa":"N","conta_receita":"S","dadosDRE":{"codigoDRE":"1.01.01","descricaoDRE":"Receita Bruta de Vendas","naoExibirDRE":"N","nivelDRE":3,"sinalDRE":"+","totalizaDRE":"N"},"definida_pelo_usuario":"S","descricao":"Arrumadeira","descricao_padrao":"Arrumadeira","id_conta_contabil":"","nao_exibir":"N","natureza":"","tag_conta_contabil":"","tipo_categoria":"","totalizadora":"N","transferencia":"N"},{"categoria_superior":"1.01","codigo":"1.01.73","codigo_dre":"1.01.01","conta_despesa":"N","conta_inativa":"N","conta_receita":"S","dadosDRE":{"codigoDRE":"1.01.01","descricaoDRE":"Receita Bruta de Vendas","naoExibirDRE":"N","nivelDRE":3,"sinalDRE":"+","totalizaDRE":"N"},"definida_pelo_usuario":"S","descricao":"Bombeiro Civil","descricao_padrao":"Bombeiro Civil","id_conta_contabil":"","nao_exibir":"N","natureza":"","tag_conta_contabil":"","tipo_categoria":"","totalizadora":"N","transferencia":"N"},{"categoria_superior":"1.01","codigo":"1.01.74","codigo_dre":"1.01.01","conta_despesa":"N","conta_inativa":"N","conta_receita":"S","dadosDRE":{"codigoDRE":"1.01.01","descricaoDRE":"Receita Bruta de Vendas","naoExibirDRE":"N","nivelDRE":3,"sinalDRE":"+","totalizaDRE":"N"},"definida_pelo_usuario":"S","descricao":"Zeladoria","descricao_padrao":"Zeladoria","id_conta_contabil":"","nao_exibir":"N","natureza":"","tag_conta_contabil":"","tipo_categoria":"","totalizadora":"N","transferencia":"N"},{"categoria_superior":"1.01","codigo":"1.01.75","codigo_dre":"","conta_despesa":"N","conta_inativa":"N","conta_receita":"S","dadosDRE":{},"definida_pelo_usuario":"S","descricao":"Empréstimos LIS","descricao_padrao":"Empréstimos LIS","id_conta_contabil":"4.2.2.06.000007","nao_exibir":"N","natureza":"","tag_conta_contabil":"JUROS E COMISSÕES BANCÁRIAS","tipo_categoria":"","totalizadora":"N","transferencia":"N"},{"categoria_superior":"1.01","codigo":"1.01.76","codigo_dre":"1.01.01","conta_despesa":"N","conta_inativa":"N","conta_receita":"S","dadosDRE":{"codigoDRE":"1.01.01","descricaoDRE":"Receita Bruta de Vendas","naoExibirDRE":"N","nivelDRE":3,"sinalDRE":"+","totalizaDRE":"N"},"definida_pelo_usuario":"S","descricao":"Mensageiro","descricao_padrao":"Mensageiro","id_conta_contabil":"","nao_exibir":"N","natureza":"","tag_conta_contabil":"","tipo_categoria":"","totalizadora":"N","transferencia":"N"},{"categoria_superior":"1.01","codigo":"1.01.77","codigo_dre":"1.01.01","conta_despesa":"N","conta_inativa":"N","conta_receita":"S","dadosDRE":{"codigoDRE":"1.01.01","descricaoDRE":"Receita Bruta de Vendas","naoExibirDRE":"N","nivelDRE":3,"sinalDRE":"+","totalizaDRE":"N"},"definida_pelo_usuario":"S","descricao":"Manobrista","descricao_padrao":"Manobrista","id_conta_contabil":"","nao_exibir":"N","natureza":"","tag_conta_contabil":"","tipo_categoria":"","totalizadora":"N","transferencia":"N"},{"categoria_superior":"1.01","codigo":"1.01.78","codigo_dre":"1.01.01","conta_despesa":"N","conta_inativa":"N","conta_receita":"S","dadosDRE":{"codigoDRE":"1.01.01","descricaoDRE":"Receita Bruta de Vendas","naoExibirDRE":"N","nivelDRE":3,"sinalDRE":"+","totalizaDRE":"N"},"definida_pelo_usuario":"S","descricao":"Manutenção","descricao_padrao":"Manutenção","id_conta_contabil":"","nao_exibir":"N","natureza":"","tag_conta_contabil":"","tipo_categoria":"","totalizadora":"N","transferencia":"N"},{"categoria_superior":"1.01","codigo":"1.01.79","codigo_dre":"1.01.01","conta_despesa":"N","conta_inativa":"N","conta_receita":"S","dadosDRE":{"codigoDRE":"1.01.01","descricaoDRE":"Receita Bruta de Vendas","naoExibirDRE":"N","nivelDRE":3,"sinalDRE":"+","totalizaDRE":"N"},"definida_pelo_usuario":"S","descricao":"Auxiliar de  Manutenção","descricao_padrao":"Auxiliar de  Manutenção","id_conta_contabil":"","nao_exibir":"N","natureza":"","tag_conta_contabil":"","tipo_categoria":"","totalizadora":"N","transferencia":"N"},{"categoria_superior":"1.01","codigo":"1.01.80","codigo_dre":"1.01.01","conta_despesa":"N","conta_inativa":"N","conta_receita":"S","dadosDRE":{"codigoDRE":"1.01.01","descricaoDRE":"Receita Bruta de Vendas","naoExibirDRE":"N","nivelDRE":3,"sinalDRE":"+","totalizaDRE":"N"},"definida_pelo_usuario":"S","descricao":"Aux. Manutenção Loja","descricao_padrao":"Aux. Manutenção Loja","id_conta_contabil":"","nao_exibir":"N","natureza":"","tag_conta_contabil":"","tipo_categoria":"","totalizadora":"N","transferencia":"N"},{"categoria_superior":"1.01","codigo":"1.01.81","codigo_dre":"1.01.01","conta_despesa":"N","conta_inativa":"N","conta_receita":"S","dadosDRE":{"codigoDRE":"1.01.01","descricaoDRE":"Receita Bruta de Vendas","naoExibirDRE":"N","nivelDRE":3,"sinalDRE":"+","totalizaDRE":"N"},"definida_pelo_usuario":"S","descricao":"Aux. Manutenção Oficina","descricao_padrao":"Aux. Manutenção Oficina","id_conta_contabil":"","nao_exibir":"N","natureza":"","tag_conta_contabil":"","tipo_categoria":"","totalizadora":"N","transferencia":"N"},{"categoria_superior":"1.01","codigo":"1.01.82","codigo_dre":"1.01.01","conta_despesa":"N","conta_inativa":"N","conta_receita":"S","dadosDRE":{"codigoDRE":"1.01.01","descricaoDRE":"Receita Bruta de Vendas","naoExibirDRE":"N","nivelDRE":3,"sinalDRE":"+","totalizaDRE":"N"},"definida_pelo_usuario":"S","descricao":"Aux. Manutenção Concessionária","descricao_padrao":"Aux. Manutenção Concessionária","id_conta_contabil":"","nao_exibir":"N","natureza":"","tag_conta_contabil":"","tipo_categoria":"","totalizadora":"N","transferencia":"N"},{"categoria_superior":"1.01","codigo":"1.01.83","codigo_dre":"1.01.01","conta_despesa":"N","conta_inativa":"N","conta_receita":"S","dadosDRE":{"codigoDRE":"1.01.01","descricaoDRE":"Receita Bruta de Vendas","naoExibirDRE":"N","nivelDRE":3,"sinalDRE":"+","totalizaDRE":"N"},"definida_pelo_usuario":"S","descricao":"Aux. Manutenção Funilaria","descricao_padrao":"Aux. Manutenção Funilaria","id_conta_contabil":"","nao_exibir":"N","natureza":"","tag_conta_contabil":"","tipo_categoria":"","totalizadora":"N","transferencia":"N"},{"categoria_superior":"1.01","codigo":"1.01.84","codigo_dre":"1.01.01","conta_despesa":"N","conta_inativa":"N","conta_receita":"S","dadosDRE":{"codigoDRE":"1.01.01","descricaoDRE":"Receita Bruta de Vendas","naoExibirDRE":"N","nivelDRE":3,"sinalDRE":"+","totalizaDRE":"N"},"definida_pelo_usuario":"S","descricao":"Jardinagem","descricao_padrao":"Jardinagem","id_conta_contabil":"","nao_exibir":"N","natureza":"","tag_conta_contabil":"","tipo_categoria":"","totalizadora":"N","transferencia":"N"},{"categoria_superior":"1.01","codigo":"1.01.85","codigo_dre":"1.01.01","conta_despesa":"N","conta_inativa":"N","conta_receita":"S","dadosDRE":{"codigoDRE":"1.01.01","descricaoDRE":"Receita Bruta de Vendas","naoExibirDRE":"N","nivelDRE":3,"sinalDRE":"+","totalizaDRE":"N"},"definida_pelo_usuario":"S","descricao":"Retenções","descricao_padrao":"Retenções","id_conta_contabil":"","nao_exibir":"N","natureza":"","tag_conta_contabil":"","tipo_categoria":"","totalizadora":"N","transferencia":"N"},{"categoria_superior":"1.01","codigo":"1.01.86","codigo_dre":"1.01.01","conta_despesa":"N","conta_inativa":"N","conta_receita":"S","dadosDRE":{"codigoDRE":"1.01.01","descricaoDRE":"Receita Bruta de Vendas","naoExibirDRE":"N","nivelDRE":3,"sinalDRE":"+","totalizaDRE":"N"},"definida_pelo_usuario":"S","descricao":"Instalações de Equipamentos","descricao_padrao":"Instalações de Equipamentos","id_conta_contabil":"","nao_exibir":"N","natureza":"","tag_conta_contabil":"","tipo_categoria":"","totalizadora":"N","transferencia":"N"},{"categoria_superior":"1.01","codigo":"1.01.87","codigo_dre":"1.01.01","conta_despesa":"N","conta_inativa":"N","conta_receita":"S","dadosDRE":{"codigoDRE":"1.01.01","descricaoDRE":"Receita Bruta de Vendas","naoExibirDRE":"N","nivelDRE":3,"sinalDRE":"+","totalizaDRE":"N"},"definida_pelo_usuario":"S","descricao":"Tratamento de Piso","descricao_padrao":"Tratamento de Piso","id_conta_contabil":"","nao_exibir":"N","natureza":"","tag_conta_contabil":"","tipo_categoria":"","totalizadora":"N","transferencia":"N"},{"categoria_superior":"1.01","codigo":"1.01.88","codigo_dre":"1.01.01","conta_despesa":"N","conta_inativa":"N","conta_receita":"S","dadosDRE":{"codigoDRE":"1.01.01","descricaoDRE":"Receita Bruta de Vendas","naoExibirDRE":"N","nivelDRE":3,"sinalDRE":"+","totalizaDRE":"N"},"definida_pelo_usuario":"S","descricao":"Venda Produtos","descricao_padrao":"Venda Produtos","id_conta_contabil":"","nao_exibir":"N","natureza":"","tag_conta_contabil":"","tipo_categoria":"","totalizadora":"N","transferencia":"N"},{"categoria_superior":"1.01","codigo":"1.01.89","codigo_dre":"1.01.01","conta_despesa":"N","conta_inativa":"N","conta_receita":"S","dadosDRE":{"codigoDRE":"1.01.01","descricaoDRE":"Receita Bruta de Vendas","naoExibirDRE":"N","nivelDRE":3,"sinalDRE":"+","totalizaDRE":"N"},"definida_pelo_usuario":"S","descricao":"Recepção","descricao_padrao":"Recepção","id_conta_contabil":"","nao_exibir":"N","natureza":"","tag_conta_contabil":"","tipo_categoria":"","totalizadora":"N","transferencia":"N"},{"categoria_superior":"1.01","codigo":"1.01.90","codigo_dre":"1.01.01","conta_despesa":"N","conta_inativa":"N","conta_receita":"S","dadosDRE":{"codigoDRE":"1.01.01","descricaoDRE":"Receita Bruta de Vendas","naoExibirDRE":"N","nivelDRE":3,"sinalDRE":"+","totalizaDRE":"N"},"definida_pelo_usuario":"S","descricao":"Locação de Equipamentos","descricao_padrao":"Locação de Equipamentos","id_conta_contabil":"","nao_exibir":"N","natureza":"","tag_conta_contabil":"","tipo_categoria":"","totalizadora":"N","transferencia":"N"},{"categoria_superior":"1.01","codigo":"1.01.91","codigo_dre":"1.01.01","conta_despesa":"N","conta_inativa":"N","conta_receita":"S","dadosDRE":{"codigoDRE":"1.01.01","descricaoDRE":"Receita Bruta de Vendas","naoExibirDRE":"N","nivelDRE":3,"sinalDRE":"+","totalizaDRE":"N"},"definida_pelo_usuario":"S","descricao":"Manutenção de Sistema de Acesso","descricao_padrao":"Manutenção de Sistema de Acesso","id_conta_contabil":"","nao_exibir":"N","natureza":"","tag_conta_contabil":"","tipo_categoria":"","totalizadora":"N","transferencia":"N"},{"categoria_superior":"1.01","codigo":"1.01.92","codigo_dre":"1.01.01","conta_despesa":"N","conta_inativa":"N","conta_receita":"S","dadosDRE":{"codigoDRE":"1.01.01","descricaoDRE":"Receita Bruta de Vendas","naoExibirDRE":"N","nivelDRE":3,"sinalDRE":"+","totalizaDRE":"N"},"definida_pelo_usuario":"S","descricao":"Locação de Varredeira","descricao_padrao":"Locação de Varredeira","id_conta_contabil":"","nao_exibir":"N","natureza":"","tag_conta_contabil":"","tipo_categoria":"","totalizadora":"N","transferencia":"N"},{"categoria_superior":"1.01","codigo":"1.01.93","codigo_dre":"1.01.01","conta_despesa":"N","conta_inativa":"N","conta_receita":"S","dadosDRE":{"codigoDRE":"1.01.01","descricaoDRE":"Receita Bruta de Vendas","naoExibirDRE":"N","nivelDRE":3,"sinalDRE":"+","totalizaDRE":"N"},"definida_pelo_usuario":"S","descricao":"Instalação de CFTV e Alarmes","descricao_padrao":"Instalação de CFTV e Alarmes","id_conta_contabil":"","nao_exibir":"N","natureza":"","tag_conta_contabil":"","tipo_categoria":"","totalizadora":"N","transferencia":"N"},{"categoria_superior":"1.01","codigo":"1.01.94","codigo_dre":"1.01.01","conta_despesa":"N","conta_inativa":"N","conta_receita":"S","dadosDRE":{"codigoDRE":"1.01.01","descricaoDRE":"Receita Bruta de Vendas","naoExibirDRE":"N","nivelDRE":3,"sinalDRE":"+","totalizaDRE":"N"},"definida_pelo_usuario":"S","descricao":"Instalação de Interfones e Tabletes","descricao_padrao":"Instalação de Interfones e Tabletes","id_conta_contabil":"","nao_exibir":"N","natureza":"","tag_conta_contabil":"","tipo_categoria":"","totalizadora":"N","transferencia":"N"},{"categoria_superior":"1.01","codigo":"1.01.95","codigo_dre":"1.01.01","conta_despesa":"N","conta_inativa":"N","conta_receita":"S","dadosDRE":{"codigoDRE":"1.01.01","descricaoDRE":"Receita Bruta de Vendas","naoExibirDRE":"N","nivelDRE":3,"sinalDRE":"+","totalizaDRE":"N"},"definida_pelo_usuario":"S","descricao":"Instalação Controle de Acesso","descricao_padrao":"Instalação Controle de Acesso","id_conta_contabil":"","nao_exibir":"N","natureza":"","tag_conta_contabil":"","tipo_categoria":"","totalizadora":"N","transferencia":"N"},{"categoria_superior":"1.01","codigo":"1.01.96","codigo_dre":"1.01.01","conta_despesa":"N","conta_inativa":"N","conta_receita":"S","dadosDRE":{"codigoDRE":"1.01.01","descricaoDRE":"Receita Bruta de Vendas","naoExibirDRE":"N","nivelDRE":3,"sinalDRE":"+","totalizaDRE":"N"},"definida_pelo_usuario":"S","descricao":"Portaria Remota","descricao_padrao":"Portaria Remota","id_conta_contabil":"","nao_exibir":"N","natureza":"","tag_conta_contabil":"","tipo_categoria":"","totalizadora":"N","transferencia":"N"},{"categoria_superior":"1.01","codigo":"1.01.97","codigo_dre":"1.01.01","conta_despesa":"N","conta_inativa":"N","conta_receita":"S","dadosDRE":{"codigoDRE":"1.01.01","descricaoDRE":"Receita Bruta de Vendas","naoExibirDRE":"N","nivelDRE":3,"sinalDRE":"+","totalizaDRE":"N"},"definida_pelo_usuario":"S","descricao":"Monitor. Remoto/Comod/Equip","descricao_padrao":"Monitor. Remoto/Comod/Equip","id_conta_contabil":"","nao_exibir":"N","natureza":"","tag_conta_contabil":"","tipo_categoria":"","totalizadora":"N","transferencia":"N"},{"categoria_superior":"1.01","codigo":"1.01.98","codigo_dre":"1.01.01","conta_despesa":"N","conta_inativa":"N","conta_receita":"S","dadosDRE":{"codigoDRE":"1.01.01","descricaoDRE":"Receita Bruta de Vendas","naoExibirDRE":"N","nivelDRE":3,"sinalDRE":"+","totalizaDRE":"N"},"definida_pelo_usuario":"S","descricao":"Instalação de CFTV","descricao_padrao":"Instalação de CFTV","id_conta_contabil":"","nao_exibir":"N","natureza":"","tag_conta_contabil":"","tipo_categoria":"","totalizadora":"N","transferencia":"N"},{"categoria_superior":"1.01","codigo":"1.01.99","codigo_dre":"1.01.01","conta_despesa":"N","conta_inativa":"N","conta_receita":"S","dadosDRE":{"codigoDRE":"1.01.01","descricaoDRE":"Receita Bruta de Vendas","naoExibirDRE":"N","nivelDRE":3,"sinalDRE":"+","totalizaDRE":"N"},"definida_pelo_usuario":"S","descricao":"Fotovoltaica","descricao_padrao":"Fotovoltaica","id_conta_contabil":"","nao_exibir":"N","natureza":"","tag_conta_contabil":"","tipo_categoria":"","totalizadora":"N","transferencia":"N"},{"categoria_superior":"1","codigo":"1.02","codigo_dre":"","conta_despesa":"N","conta_inativa":"N","conta_receita":"S","dadosDRE":{},"definida_pelo_usuario":"N","descricao":"Receitas Indiretas","descricao_padrao":"Receitas Indiretas","id_conta_contabil":"","nao_exibir":"N","natureza":"","tag_conta_contabil":"","tipo_categoria":"","totalizadora":"S","transferencia":"N"},{"categoria_superior":"1.02","codigo":"1.02.01","codigo_dre":"1.11.01","conta_despesa":"N","conta_inativa":"N","conta_receita":"S","dadosDRE":{"codigoDRE":"1.11.01","descricaoDRE":"Outras Receitas","naoExibirDRE":"N","nivelDRE":3,"sinalDRE":"+","totalizaDRE":"N"},"definida_pelo_usuario":"N","descricao":"Dividendos Recebidos","descricao_padrao":"Dividendos Recebidos","id_conta_contabil":"1.1.3.05.000001","nao_exibir":"N","natureza":"Esta categoria deve ser utilizada para receitas provenientes de recebimento de lucros gerados por empresas das quais a sua empresa é dona, ou seja, se a sua empresa é dona ou acionista de outra empresa, quando você receber um repasse que seja originado exclusivamente de lucros gerados após todas as despesas diretas e indiretas pagas, você deve classificar nesta categoria.","tag_conta_contabil":"ADIANTAMENTOS A FORNECEDORES","tipo_categoria":"","totalizadora":"N","transferencia":"N"},{"categoria_superior":"1.02","codigo":"1.02.02","codigo_dre":"1.11.01","conta_despesa":"N","conta_inativa":"N","conta_receita":"S","dadosDRE":{"codigoDRE":"1.11.01","descricaoDRE":"Outras Receitas","naoExibirDRE":"N","nivelDRE":3,"sinalDRE":"+","totalizaDRE":"N"},"definida_pelo_usuario":"N","descricao":"Rendimentos de Aplicações","descricao_padrao":"Rendimentos de Aplicações","id_conta_contabil":"3.1.3.01.000001","nao_exibir":"N","natureza":"Esta categoria deve ser utilizada para registrar uma receita de juros provenientes de uma determinada aplicação financeira ou ganho de capital. Por exemplo: juros obtidos por uma aplicação em ações na bolsa, ou por um fundo de investimento em seu banco.","tag_conta_contabil":"JUROS DE APLICAÇÕES","tipo_categoria":"","totalizadora":"N","transferencia":"N"},{"categoria_superior":"1.02","codigo":"1.02.95","codigo_dre":"","conta_despesa":"N","conta_inativa":"N","conta_receita":"S","dadosDRE":{},"definida_pelo_usuario":"S","descricao":"+ Cobertura Bradesco","descricao_padrao":"+ Cobertura Bradesco","id_conta_contabil":"1.1.2.01.000001","nao_exibir":"N","natureza":"","tag_conta_contabil":"CLIENTES","tipo_categoria":"","totalizadora":"N","transferencia":"N"},{"categoria_superior":"1.02","codigo":"1.02.96","codigo_dre":"","conta_despesa":"N","conta_inativa":"N","conta_receita":"S","dadosDRE":{},"definida_pelo_usuario":"S","descricao":"+ Cobertura Caixa","descricao_padrao":"+ Cobertura Caixa","id_conta_contabil":"1.1.1.01.000001","nao_exibir":"N","natureza":"","tag_conta_contabil":"CAIXA GERAL","tipo_categoria":"","totalizadora":"N","transferencia":"N"},{"categoria_superior":"1.02","codigo":"1.02.97","codigo_dre":"","conta_despesa":"N","conta_inativa":"N","conta_receita":"S","dadosDRE":{},"definida_pelo_usuario":"S","descricao":"PGTOS RP P/ GSIA","descricao_padrao":"PGTOS RP P/ GSIA","id_conta_contabil":"1.1.2.01.000030","nao_exibir":"N","natureza":"","tag_conta_contabil":"RP GESTAO DE SERVICOS LTDA","tipo_categoria":"","totalizadora":"N","transferencia":"N"},{"categoria_superior":"1.02","codigo":"1.02.98","codigo_dre":"","conta_despesa":"N","conta_inativa":"N","conta_receita":"S","dadosDRE":{},"definida_pelo_usuario":"S","descricao":"Arrumadeiras","descricao_padrao":"Arrumadeiras","id_conta_contabil":"","nao_exibir":"N","natureza":"","tag_conta_contabil":"","tipo_categoria":"","totalizadora":"N","transferencia":"N"},{"categoria_superior":"1.02","codigo":"1.02.99","codigo_dre":"","conta_despesa":"N","conta_inativa":"N","conta_receita":"S","dadosDRE":{},"definida_pelo_usuario":"S","descricao":"Portaria 24 Hs....","descricao_padrao":"Portaria 24 Hs....","id_conta_contabil":"","nao_exibir":"N","natureza":"","tag_conta_contabil":"","tipo_categoria":"","totalizadora":"N","transferencia":"N"},{"categoria_superior":"1","codigo":"1.03","codigo_dre":"","conta_despesa":"N","conta_inativa":"N","conta_receita":"S","dadosDRE":{},"definida_pelo_usuario":"N","descricao":"Devoluções","descricao_padrao":"Devoluções","id_conta_contabil":"","nao_exibir":"N","natureza":"","tag_conta_contabil":"","tipo_categoria":"","totalizadora":"S","transferencia":"N"},{"categoria_superior":"1.03","codigo":"1.03.01","codigo_dre":"2.01.02","conta_despesa":"N","conta_inativa":"N","conta_receita":"S","dadosDRE":{"codigoDRE":"2.01.02","descricaoDRE":"Recuperação de Despesas Variáveis","naoExibirDRE":"N","nivelDRE":3,"sinalDRE":"+","totalizaDRE":"N"},"definida_pelo_usuario":"N","descricao":"Devoluções de Compra de Mercadoria de Revenda","descricao_padrao":"Devoluções de Compra de Mercadoria de Revenda","id_conta_contabil":"","nao_exibir":"N","natureza":"Utilize esta categoria para classificar uma entrada de dinheiro proveniente da devolução de uma compra que você fez de mercadoria para revender. Exemplo: você devolve uma determinada compra de produtos ao seu fornecedor e o mesmo lhe devolve o dinheiro que você pagou. Se a sua empresa é exclusivamente prestadora de serviços e não vende produtos, esta categoria pode ser inativada ou desabilitada.","tag_conta_contabil":"","tipo_categoria":"","totalizadora":"N","transferencia":"N"},{"categoria_superior":"1.03","codigo":"1.03.02","codigo_dre":"2.01.02","conta_despesa":"N","conta_inativa":"N","conta_receita":"S","dadosDRE":{"codigoDRE":"2.01.02","descricaoDRE":"Recuperação de Despesas Variáveis","naoExibirDRE":"N","nivelDRE":3,"sinalDRE":"+","totalizaDRE":"N"},"definida_pelo_usuario":"N","descricao":"Devoluções de Compra de Material de Consumo","descricao_padrao":"Devoluções de Compra de Material de Consumo","id_conta_contabil":"","nao_exibir":"N","natureza":"Utilize esta categoria para classificar uma entrada de dinheiro proveniente da devolução de uma compra que você fez de produto para consumo interno. Exemplo: você devolve uma determinada compra de materiais de consumo ao seu fornecedor e o mesmo lhe devolve o dinheiro que você pagou.","tag_conta_contabil":"","tipo_categoria":"","totalizadora":"N","transferencia":"N"},{"categoria_superior":"1.03","codigo":"1.03.03","codigo_dre":"2.01.02","conta_despesa":"N","conta_inativa":"N","conta_receita":"S","dadosDRE":{"codigoDRE":"2.01.02","descricaoDRE":"Recuperação de Despesas Variáveis","naoExibirDRE":"N","nivelDRE":3,"sinalDRE":"+","totalizaDRE":"N"},"definida_pelo_usuario":"N","descricao":"Devoluções de Compra de Matéria Prima","descricao_padrao":"Devoluções de Compra de Matéria Prima","id_conta_contabil":"","nao_exibir":"N","natureza":"Utilize esta categoria para classificar uma entrada de dinheiro proveniente da devolução de produtos ou insumos utilizados como matéria prima em sua operação. Exemplo: você devolve uma determinada compra de produtos ao seu fornecedor e o mesmo lhe devolve o dinheiro que você pagou.","tag_conta_contabil":"","tipo_categoria":"","totalizadora":"N","transferencia":"N"},{"categoria_superior":"1.03","codigo":"1.03.04","codigo_dre":"","conta_despesa":"N","conta_inativa":"N","conta_receita":"S","dadosDRE":{},"definida_pelo_usuario":"N","descricao":"Devoluções de Compra de Ativo","descricao_padrao":"Devoluções de Compra de Ativo","id_conta_contabil":"","nao_exibir":"N","natureza":"Utilize esta categoria para classificar uma entrada de dinheiro proveniente da devolução de bens que você fez para ativo. Exemplo: você devolve uma determinada compra de veículo e a concessionária lhe devolve o dinheiro que você pagou.","tag_conta_contabil":"","tipo_categoria":"","totalizadora":"N","transferencia":"N"},{"categoria_superior":"1.03","codigo":"1.03.26","codigo_dre":"2.01.02","conta_despesa":"N","conta_inativa":"N","conta_receita":"S","dadosDRE":{"codigoDRE":"2.01.02","descricaoDRE":"Recuperação de Despesas Variáveis","naoExibirDRE":"N","nivelDRE":3,"sinalDRE":"+","totalizaDRE":"N"},"definida_pelo_usuario":"N","descricao":"Devolução","descricao_padrao":"Devolução","id_conta_contabil":"","nao_exibir":"N","natureza":"Utilize esta categoria para classificar uma entrada de dinheiro proveniente da devolução de uma compra que você fez de serviços. Exemplo: você devolve ou questiona/reclama uma determinada compra de um serviço tomado ao seu fornecedor e o mesmo lhe devolve o dinheiro que você pagou.","tag_conta_contabil":"","tipo_categoria":"","totalizadora":"N","transferencia":"N"},{"categoria_superior":"1","codigo":"1.04","codigo_dre":"","conta_despesa":"N","conta_inativa":"N","conta_receita":"S","dadosDRE":{},"definida_pelo_usuario":"N","descricao":"Outras Entradas","descricao_padrao":"Outras Entradas","id_conta_contabil":"","nao_exibir":"N","natureza":"","tag_conta_contabil":"","tipo_categoria":"","totalizadora":"S","transferencia":"N"},{"categoria_superior":"1.04","codigo":"1.04.01","codigo_dre":"","conta_despesa":"N","conta_inativa":"N","conta_receita":"S","dadosDRE":{},"definida_pelo_usuario":"N","descricao":"Adiantamento de Clientes","descricao_padrao":"Adiantamento de Clientes","id_conta_contabil":"1.1.3.05.000001","nao_exibir":"N","natureza":"Utilize esta categoria para classificar entradas de dinheiro de clientes sobre produtos ou serviços que você ainda não emitiu nota fiscal.","tag_conta_contabil":"ADIANTAMENTOS A FORNECEDORES","tipo_categoria":"","totalizadora":"N","transferencia":"N"},{"categoria_superior":"1.04","codigo":"1.04.02","codigo_dre":"2.01.02","conta_despesa":"N","conta_inativa":"N","conta_receita":"S","dadosDRE":{"codigoDRE":"2.01.02","descricaoDRE":"Recuperação de Despesas Variáveis","naoExibirDRE":"N","nivelDRE":3,"sinalDRE":"+","totalizaDRE":"N"},"definida_pelo_usuario":"N","descricao":"Reembolso de Despesas","descricao_padrao":"Reembolso de Despesas","id_conta_contabil":"4.2.2.04.000099","nao_exibir":"N","natureza":"Utilize esta categoria para classificar entradas de dinheiro advindas de reembolsos de despesas (comprovadas por relatórios de despesas) recebidas de clientes sobre gastos que ocorreram na sua prestação de serviço.","tag_conta_contabil":"DESPESAS GERAIS","tipo_categoria":"","totalizadora":"N","transferencia":"N"},{"categoria_superior":"1.04","codigo":"1.04.03","codigo_dre":"","conta_despesa":"N","conta_inativa":"N","conta_receita":"S","dadosDRE":{},"definida_pelo_usuario":"N","descricao":"Empréstimos Bancários","descricao_padrao":"Empréstimos Bancários","id_conta_contabil":"4.2.2.06.000012","nao_exibir":"N","natureza":"Utilize esta categoria para identificar lançamentos de entradas de dinheiro advindas de empréstimos que você contraiu.","tag_conta_contabil":"EMPRESTIMO / FINANCIAMENTO","tipo_categoria":"","totalizadora":"N","transferencia":"N"},{"categoria_superior":"1.04","codigo":"1.04.04","codigo_dre":"","conta_despesa":"N","conta_inativa":"N","conta_receita":"S","dadosDRE":{},"definida_pelo_usuario":"N","descricao":"Aumento de Capital","descricao_padrao":"Aumento de Capital","id_conta_contabil":"2.3.1.02.000001","nao_exibir":"N","natureza":"Utilize esta categoria para entrada de dinheiro investido pelos os sócios na empresa.","tag_conta_contabil":"CAPITAL A INTEGRALIZAR","tipo_categoria":"","totalizadora":"N","transferencia":"N"},{"categoria_superior":"1.04","codigo":"1.04.05","codigo_dre":"","conta_despesa":"N","conta_inativa":"N","conta_receita":"S","dadosDRE":{},"definida_pelo_usuario":"N","descricao":"Venda de Participações","descricao_padrao":"Venda de Participações","id_conta_contabil":"","nao_exibir":"N","natureza":"Utilize esta categoria para entradas de dinheiro advindo da venda parcial ou total de outras empresas das quais a sua empresa era dona.","tag_conta_contabil":"","tipo_categoria":"","totalizadora":"N","transferencia":"N"},{"categoria_superior":"1.04","codigo":"1.04.06","codigo_dre":"","conta_despesa":"N","conta_inativa":"N","conta_receita":"S","dadosDRE":{},"definida_pelo_usuario":"N","descricao":"Juros","descricao_padrao":"Juros","id_conta_contabil":"3.1.3.01.000002","nao_exibir":"N","natureza":"Utilize esta categoria para identificar receitas de venda de ativos, tais como veículos, máquinas e equipamentos que não foram comprados para revender.","tag_conta_contabil":"JUROS ATIVOS","tipo_categoria":"","totalizadora":"N","transferencia":"N"},{"categoria_superior":"1.04","codigo":"1.04.90","codigo_dre":"","conta_despesa":"N","conta_inativa":"N","conta_receita":"S","dadosDRE":{},"definida_pelo_usuario":"S","descricao":"+ Pagamento GSIA-RPSIA","descricao_padrao":"+ Pagamento GSIA-RPSIA","id_conta_contabil":"1.1.3.05.000001","nao_exibir":"N","natureza":"","tag_conta_contabil":"ADIANTAMENTOS A FORNECEDORES","tipo_categoria":"","totalizadora":"N","transferencia":"N"},{"categoria_superior":"1.04","codigo":"1.04.91","codigo_dre":"","conta_despesa":"N","conta_inativa":"N","conta_receita":"S","dadosDRE":{},"definida_pelo_usuario":"S","descricao":"Devolução de Empréstimo","descricao_padrao":"Devolução de Empréstimo","id_conta_contabil":"2.1.1.01.000001","nao_exibir":"N","natureza":"","tag_conta_contabil":"EMPRÉSTIMO CAIXA ECONOMICA","tipo_categoria":"","totalizadora":"N","transferencia":"N"},{"categoria_superior":"1.04","codigo":"1.04.92","codigo_dre":"","conta_despesa":"N","conta_inativa":"N","conta_receita":"S","dadosDRE":{},"definida_pelo_usuario":"S","descricao":"Parcelamento Limite","descricao_padrao":"Parcelamento Limite","id_conta_contabil":"2.1.1.01.000001","nao_exibir":"N","natureza":"","tag_conta_contabil":"EMPRÉSTIMO CAIXA ECONOMICA","tipo_categoria":"","totalizadora":"N","transferencia":"N"},{"categoria_superior":"1.04","codigo":"1.04.93","codigo_dre":"","conta_despesa":"N","conta_inativa":"N","conta_receita":"S","dadosDRE":{},"definida_pelo_usuario":"S","descricao":"Desconto Duplicatas","descricao_padrao":"Desconto Duplicatas","id_conta_contabil":"1.1.3.05.000001","nao_exibir":"N","natureza":"","tag_conta_contabil":"ADIANTAMENTOS A FORNECEDORES","tipo_categoria":"","totalizadora":"N","transferencia":"N"},{"categoria_superior":"1.04","codigo":"1.04.94","codigo_dre":"","conta_despesa":"N","conta_inativa":"N","conta_receita":"S","dadosDRE":{},"definida_pelo_usuario":"S","descricao":"+ Pagamentos Caixa","descricao_padrao":"+ Pagamentos Caixa","id_conta_contabil":"1.1.1.01.000001","nao_exibir":"N","natureza":"","tag_conta_contabil":"CAIXA GERAL","tipo_categoria":"","totalizadora":"N","transferencia":"N"},{"categoria_superior":"1.04","codigo":"1.04.95","codigo_dre":"","conta_despesa":"N","conta_inativa":"N","conta_receita":"S","dadosDRE":{},"definida_pelo_usuario":"S","descricao":"Prêmios de Seguros / Sinistros","descricao_padrao":"Prêmios de Seguros / Sinistros","id_conta_contabil":"4.2.2.04.000005","nao_exibir":"N","natureza":"Utilize esta categoria para classificar uma entrada de dinheiro proveniente do recebimento de um sinistro de seguro. Por exemplo: Se a sua empresa foi indenizada pelo seguro de qualquer ocorrência como: um automóvel que foi furtado, roubo de notebook de um funcionário, roubo do escritório e outros.","tag_conta_contabil":"SEGUROS","tipo_categoria":"","totalizadora":"N","transferencia":"N"}]